screenpy_appium/__init__.py
screenpy_appium/__version__.py
screenpy_appium/abilities/__init__.py
screenpy_appium/abilities/use_a_mobile_device.py
screenpy_appium/abilities/use_an_android_device.py
screenpy_appium/abilities/use_an_ios_device.py
screenpy_appium/actions/__init__.py
screenpy_appium/actions/clear.py
screenpy_appium/actions/enter.py
screenpy_appium/actions/tap.py
screenpy_appium/common.py
screenpy_appium/exceptions.py
screenpy_appium/py.typed
screenpy_appium/questions/__init__.py
screenpy_appium/questions/attribute.py
screenpy_appium/questions/element.py
screenpy_appium/questions/list.py
screenpy_appium/questions/number.py
screenpy_appium/questions/text.py
screenpy_appium/resolutions/__init__.py
screenpy_appium/resolutions/custom_matchers/__init__.py
screenpy_appium/resolutions/custom_matchers/is_tappable_element.py
screenpy_appium/resolutions/custom_matchers/is_visible_element.py
screenpy_appium/resolutions/is_tappable.py
screenpy_appium/resolutions/is_visible.py
screenpy_appium/target.py
screenpy_appium-0.0.2.dist-info/LICENSE
screenpy_appium-0.0.2.dist-info/METADATA
screenpy_appium-0.0.2.dist-info/WHEEL
screenpy_appium-0.0.2.dist-info/RECORD
