Metadata-Version: 2.1
Name: screenpy_appium
Version: 0.0.2
Summary: ScreenPy extension that enables interacting with Appium.
Home-page: https://github.com/ScreenPyHQ/screenpy_appium
License: MIT
Author: Perry Goy
Author-email: perry.goy@gmail.com
Maintainer: Marcel Wilson
Requires-Python: >=3.8,<4.0
Classifier: Development Status :: 5 - Production/Stable
Classifier: Intended Audience :: Developers
Classifier: License :: OSI Approved :: MIT License
Classifier: Natural Language :: English
Classifier: Operating System :: OS Independent
Classifier: Programming Language :: Python :: 3
Classifier: Programming Language :: Python :: 3.8
Classifier: Programming Language :: Python :: 3.9
Classifier: Programming Language :: Python :: 3.10
Classifier: Programming Language :: Python :: 3.11
Classifier: Programming Language :: Python :: 3.12
Classifier: Programming Language :: Python :: 3 :: Only
Classifier: Topic :: Software Development :: Quality Assurance
Classifier: Topic :: Software Development :: Testing
Classifier: Topic :: Software Development :: Testing :: BDD
Provides-Extra: dev
Provides-Extra: docs
Provides-Extra: test
Requires-Dist: Appium-Python-Client (>=2.0)
Requires-Dist: black ; extra == "dev"
Requires-Dist: coverage ; extra == "dev" or extra == "test"
Requires-Dist: cruft ; extra == "dev"
Requires-Dist: mypy ; extra == "dev"
Requires-Dist: pre-commit ; extra == "dev"
Requires-Dist: pytest ; extra == "dev" or extra == "test"
Requires-Dist: pytest-mock ; extra == "dev" or extra == "test"
Requires-Dist: ruff (>=0.2.0) ; extra == "dev"
Requires-Dist: screenpy (>=4.0.2)
Requires-Dist: sphinx ; extra == "dev" or extra == "docs"
Requires-Dist: sphinx-rtd-theme ; extra == "dev" or extra == "docs"
Requires-Dist: tox ; extra == "dev"
Project-URL: Documentation, https://screenpy-appium-docs.readthedocs.io
Project-URL: Repository, https://github.com/ScreenPyHQ/screenpy_appium
